[{"id":"26041412460+F","market_and_exchange_names":"DJIA Consolidated - CHICAGO BOARD OF TRADE","report_date_as_yyyy_mm_dd":"2026-04-14T00:00:00.000","yyyy_report_week_ww":"2026 Report Week 15","contract_market_name":"DJIA Consolidated","cftc_contract_market_code":"12460+","cftc_market_code":"CBT ","cftc_region_code":"CHI","cftc_commodity_code":"124 ","commodity_name":"DOW JONES BROAD BASED INDICES","open_interest_all":"72089","noncomm_positions_long_all":"7010","noncomm_positions_short_all":"11610","noncomm_postions_spread_all":"3165","comm_positions_long_all":"47901","comm_positions_short_all":"46680","tot_rept_positions_long_all":"58077","tot_rept_positions_short":"61455","nonrept_positions_long_all":"14012","nonrept_positions_short_all":"10634","open_interest_old":"72089","noncomm_positions_long_old":"7010","noncomm_positions_short_old":"11610","noncomm_positions_spread":"3165","comm_positions_long_old":"47901","comm_positions_short_old":"46680","tot_rept_positions_long_old":"58077","tot_rept_positions_short_1":"61455","nonrept_positions_long_old":"14012","nonrept_positions_short_old":"10634","open_interest_other":"0","noncomm_positions_long_other":"0","noncomm_positions_short_other":"0","noncomm_positions_spread_1":"0","comm_positions_long_other":"0","comm_positions_short_other":"0","tot_rept_positions_long_other":"0","tot_rept_positions_short_2":"0","nonrept_positions_long_other":"0","nonrept_positions_short_other":"0","change_in_open_interest_all":"3532","change_in_noncomm_long_all":"1995","change_in_noncomm_short_all":"-2979","change_in_noncomm_spead_all":"2063","change_in_comm_long_all":"-1445","change_in_comm_short_all":"3500","change_in_tot_rept_long_all":"2614","change_in_tot_rept_short":"2584","change_in_nonrept_long_all":"918","change_in_nonrept_short_all":"948","pct_of_open_interest_all":"100.0","pct_of_oi_noncomm_long_all":"9.7","pct_of_oi_noncomm_short_all":"16.1","pct_of_oi_noncomm_spread":"4.4","pct_of_oi_comm_long_all":"66.4","pct_of_oi_comm_short_all":"64.8","pct_of_oi_tot_rept_long_all":"80.6","pct_of_oi_tot_rept_short":"85.2","pct_of_oi_nonrept_long_all":"19.4","pct_of_oi_nonrept_short_all":"14.8","pct_of_open_interest_old":"100.0","pct_of_oi_noncomm_long_old":"9.7","pct_of_oi_noncomm_short_old":"16.1","pct_of_oi_noncomm_spread_1":"4.4","pct_of_oi_comm_long_old":"66.4","pct_of_oi_comm_short_old":"64.8","pct_of_oi_tot_rept_long_old":"80.6","pct_of_oi_tot_rept_short_1":"85.2","pct_of_oi_nonrept_long_old":"19.4","pct_of_oi_nonrept_short_old":"14.8","pct_of_open_interest_other":"0.0","pct_of_oi_noncomm_long_other":"0.0","pct_of_oi_noncomm_short_other":"0.0","pct_of_oi_noncomm_spread_2":"0.0","pct_of_oi_comm_long_other":"0.0","pct_of_oi_comm_short_other":"0.0","pct_of_oi_tot_rept_long_other":"0.0","pct_of_oi_tot_rept_short_2":"0.0","pct_of_oi_nonrept_long_other":"0.0","pct_of_oi_nonrept_short_other":"0.0","traders_tot_all":"77","traders_noncomm_long_all":"19","traders_noncomm_short_all":"18","traders_noncomm_spread_all":"14","traders_comm_long_all":"29","traders_comm_short_all":"21","traders_tot_rept_long_all":"55","traders_tot_rept_short_all":"46","traders_tot_old":"77","traders_noncomm_long_old":"19","traders_noncomm_short_old":"18","traders_noncomm_spead_old":"14","traders_comm_long_old":"29","traders_comm_short_old":"21","traders_tot_rept_long_old":"55","traders_tot_rept_short_old":"46","traders_tot_other":"0","traders_noncomm_long_other":"0","traders_noncomm_short_other":"0","traders_noncomm_spread_other":"0","traders_comm_long_other":"0","traders_comm_short_other":"0","traders_tot_rept_long_other":"0","traders_tot_rept_short_other":"0","conc_gross_le_4_tdr_long":"40.2","conc_gross_le_4_tdr_short":"42.9","conc_gross_le_8_tdr_long":"55.1","conc_gross_le_8_tdr_short":"59.4","conc_net_le_4_tdr_long_all":"39.9","conc_net_le_4_tdr_short_all":"42.8","conc_net_le_8_tdr_long_all":"54.6","conc_net_le_8_tdr_short_all":"59.2","conc_gross_le_4_tdr_long_1":"40.2","conc_gross_le_4_tdr_short_1":"42.9","conc_gross_le_8_tdr_long_1":"55.1","conc_gross_le_8_tdr_short_1":"59.4","conc_net_le_4_tdr_long_old":"39.9","conc_net_le_4_tdr_short_old":"42.8","conc_net_le_8_tdr_long_old":"54.6","conc_net_le_8_tdr_short_old":"59.2","conc_gross_le_4_tdr_long_2":"0.0","conc_gross_le_4_tdr_short_2":"0.0","conc_gross_le_8_tdr_long_2":"0.0","conc_gross_le_8_tdr_short_2":"0.0","conc_net_le_4_tdr_long_other":"0.0","conc_net_le_4_tdr_short_other":"0.0","conc_net_le_8_tdr_long_other":"0.0","conc_net_le_8_tdr_short_other":"0.0","contract_units":"($5 X DJIA INDEX)","commodity":"DOW JONES BROAD BASED INDICES","commodity_subgroup_name":"STOCK INDICES","commodity_group_name":"FINANCIAL INSTRUMENTS","futonly_or_combined":"FutOnly"}
,{"id":"26040712460+F","market_and_exchange_names":"DJIA Consolidated - CHICAGO BOARD OF TRADE","report_date_as_yyyy_mm_dd":"2026-04-07T00:00:00.000","yyyy_report_week_ww":"2026 Report Week 14","contract_market_name":"DJIA Consolidated","cftc_contract_market_code":"12460+","cftc_market_code":"CBT ","cftc_region_code":"CHI","cftc_commodity_code":"124 ","commodity_name":"DOW JONES BROAD BASED INDICES","open_interest_all":"68557","noncomm_positions_long_all":"5015","noncomm_positions_short_all":"14589","noncomm_postions_spread_all":"1102","comm_positions_long_all":"49346","comm_positions_short_all":"43180","tot_rept_positions_long_all":"55463","tot_rept_positions_short":"58871","nonrept_positions_long_all":"13094","nonrept_positions_short_all":"9686","open_interest_old":"68557","noncomm_positions_long_old":"5015","noncomm_positions_short_old":"14589","noncomm_positions_spread":"1102","comm_positions_long_old":"49346","comm_positions_short_old":"43180","tot_rept_positions_long_old":"55463","tot_rept_positions_short_1":"58871","nonrept_positions_long_old":"13094","nonrept_positions_short_old":"9686","open_interest_other":"0","noncomm_positions_long_other":"0","noncomm_positions_short_other":"0","noncomm_positions_spread_1":"0","comm_positions_long_other":"0","comm_positions_short_other":"0","tot_rept_positions_long_other":"0","tot_rept_positions_short_2":"0","nonrept_positions_long_other":"0","nonrept_positions_short_other":"0","change_in_open_interest_all":"-2271","change_in_noncomm_long_all":"-1815","change_in_noncomm_short_all":"3653","change_in_noncomm_spead_all":"-879","change_in_comm_long_all":"1665","change_in_comm_short_all":"-2949","change_in_tot_rept_long_all":"-1028","change_in_tot_rept_short":"-175","change_in_nonrept_long_all":"-1243","change_in_nonrept_short_all":"-2096","pct_of_open_interest_all":"100.0","pct_of_oi_noncomm_long_all":"7.3","pct_of_oi_noncomm_short_all":"21.3","pct_of_oi_noncomm_spread":"1.6","pct_of_oi_comm_long_all":"72.0","pct_of_oi_comm_short_all":"63.0","pct_of_oi_tot_rept_long_all":"80.9","pct_of_oi_tot_rept_short":"85.9","pct_of_oi_nonrept_long_all":"19.1","pct_of_oi_nonrept_short_all":"14.1","pct_of_open_interest_old":"100.0","pct_of_oi_noncomm_long_old":"7.3","pct_of_oi_noncomm_short_old":"21.3","pct_of_oi_noncomm_spread_1":"1.6","pct_of_oi_comm_long_old":"72.0","pct_of_oi_comm_short_old":"63.0","pct_of_oi_tot_rept_long_old":"80.9","pct_of_oi_tot_rept_short_1":"85.9","pct_of_oi_nonrept_long_old":"19.1","pct_of_oi_nonrept_short_old":"14.1","pct_of_open_interest_other":"0.0","pct_of_oi_noncomm_long_other":"0.0","pct_of_oi_noncomm_short_other":"0.0","pct_of_oi_noncomm_spread_2":"0.0","pct_of_oi_comm_long_other":"0.0","pct_of_oi_comm_short_other":"0.0","pct_of_oi_tot_rept_long_other":"0.0","pct_of_oi_tot_rept_short_2":"0.0","pct_of_oi_nonrept_long_other":"0.0","pct_of_oi_nonrept_short_other":"0.0","traders_tot_all":"66","traders_noncomm_long_all":"9","traders_noncomm_short_all":"17","traders_noncomm_spread_all":"8","traders_comm_long_all":"26","traders_comm_short_all":"21","traders_tot_rept_long_all":"41","traders_tot_rept_short_all":"40","traders_tot_old":"66","traders_noncomm_long_old":"9","traders_noncomm_short_old":"17","traders_noncomm_spead_old":"8","traders_comm_long_old":"26","traders_comm_short_old":"21","traders_tot_rept_long_old":"41","traders_tot_rept_short_old":"40","traders_tot_other":"0","traders_noncomm_long_other":"0","traders_noncomm_short_other":"0","traders_noncomm_spread_other":"0","traders_comm_long_other":"0","traders_comm_short_other":"0","traders_tot_rept_long_other":"0","traders_tot_rept_short_other":"0","conc_gross_le_4_tdr_long":"47.6","conc_gross_le_4_tdr_short":"43.7","conc_gross_le_8_tdr_long":"60.8","conc_gross_le_8_tdr_short":"59.9","conc_net_le_4_tdr_long_all":"47.3","conc_net_le_4_tdr_short_all":"43.7","conc_net_le_8_tdr_long_all":"60.5","conc_net_le_8_tdr_short_all":"59.7","conc_gross_le_4_tdr_long_1":"47.6","conc_gross_le_4_tdr_short_1":"43.7","conc_gross_le_8_tdr_long_1":"60.8","conc_gross_le_8_tdr_short_1":"59.9","conc_net_le_4_tdr_long_old":"47.3","conc_net_le_4_tdr_short_old":"43.7","conc_net_le_8_tdr_long_old":"60.5","conc_net_le_8_tdr_short_old":"59.7","conc_gross_le_4_tdr_long_2":"0.0","conc_gross_le_4_tdr_short_2":"0.0","conc_gross_le_8_tdr_long_2":"0.0","conc_gross_le_8_tdr_short_2":"0.0","conc_net_le_4_tdr_long_other":"0.0","conc_net_le_4_tdr_short_other":"0.0","conc_net_le_8_tdr_long_other":"0.0","conc_net_le_8_tdr_short_other":"0.0","contract_units":"($5 X DJIA INDEX)","commodity":"DOW JONES BROAD BASED INDICES","commodity_subgroup_name":"STOCK INDICES","commodity_group_name":"FINANCIAL INSTRUMENTS","futonly_or_combined":"FutOnly"}
,{"id":"26033112460+F","market_and_exchange_names":"DJIA Consolidated - CHICAGO BOARD OF TRADE","report_date_as_yyyy_mm_dd":"2026-03-31T00:00:00.000","yyyy_report_week_ww":"2026 Report Week 13","contract_market_name":"DJIA Consolidated","cftc_contract_market_code":"12460+","cftc_market_code":"CBT ","cftc_region_code":"CHI","cftc_commodity_code":"124 ","commodity_name":"DOW JONES BROAD BASED INDICES","open_interest_all":"70828","noncomm_positions_long_all":"6830","noncomm_positions_short_all":"10936","noncomm_postions_spread_all":"1981","comm_positions_long_all":"47681","comm_positions_short_all":"46129","tot_rept_positions_long_all":"56491","tot_rept_positions_short":"59046","nonrept_positions_long_all":"14337","nonrept_positions_short_all":"11782","open_interest_old":"70828","noncomm_positions_long_old":"6830","noncomm_positions_short_old":"10936","noncomm_positions_spread":"1981","comm_positions_long_old":"47681","comm_positions_short_old":"46129","tot_rept_positions_long_old":"56491","tot_rept_positions_short_1":"59046","nonrept_positions_long_old":"14337","nonrept_positions_short_old":"11782","open_interest_other":"0","noncomm_positions_long_other":"0","noncomm_positions_short_other":"0","noncomm_positions_spread_1":"0","comm_positions_long_other":"0","comm_positions_short_other":"0","tot_rept_positions_long_other":"0","tot_rept_positions_short_2":"0","nonrept_positions_long_other":"0","nonrept_positions_short_other":"0","change_in_open_interest_all":"2906","change_in_noncomm_long_all":"1500","change_in_noncomm_short_all":"-957","change_in_noncomm_spead_all":"704","change_in_comm_long_all":"-679","change_in_comm_short_all":"724","change_in_tot_rept_long_all":"1524","change_in_tot_rept_short":"471","change_in_nonrept_long_all":"1382","change_in_nonrept_short_all":"2435","pct_of_open_interest_all":"100.0","pct_of_oi_noncomm_long_all":"9.6","pct_of_oi_noncomm_short_all":"15.4","pct_of_oi_noncomm_spread":"2.8","pct_of_oi_comm_long_all":"67.3","pct_of_oi_comm_short_all":"65.1","pct_of_oi_tot_rept_long_all":"79.8","pct_of_oi_tot_rept_short":"83.4","pct_of_oi_nonrept_long_all":"20.2","pct_of_oi_nonrept_short_all":"16.6","pct_of_open_interest_old":"100.0","pct_of_oi_noncomm_long_old":"9.6","pct_of_oi_noncomm_short_old":"15.4","pct_of_oi_noncomm_spread_1":"2.8","pct_of_oi_comm_long_old":"67.3","pct_of_oi_comm_short_old":"65.1","pct_of_oi_tot_rept_long_old":"79.8","pct_of_oi_tot_rept_short_1":"83.4","pct_of_oi_nonrept_long_old":"20.2","pct_of_oi_nonrept_short_old":"16.6","pct_of_open_interest_other":"0.0","pct_of_oi_noncomm_long_other":"0.0","pct_of_oi_noncomm_short_other":"0.0","pct_of_oi_noncomm_spread_2":"0.0","pct_of_oi_comm_long_other":"0.0","pct_of_oi_comm_short_other":"0.0","pct_of_oi_tot_rept_long_other":"0.0","pct_of_oi_tot_rept_short_2":"0.0","pct_of_oi_nonrept_long_other":"0.0","pct_of_oi_nonrept_short_other":"0.0","traders_tot_all":"80","traders_noncomm_long_all":"17","traders_noncomm_short_all":"20","traders_noncomm_spread_all":"13","traders_comm_long_all":"27","traders_comm_short_all":"23","traders_tot_rept_long_all":"51","traders_tot_rept_short_all":"49","traders_tot_old":"80","traders_noncomm_long_old":"17","traders_noncomm_short_old":"20","traders_noncomm_spead_old":"13","traders_comm_long_old":"27","traders_comm_short_old":"23","traders_tot_rept_long_old":"51","traders_tot_rept_short_old":"49","traders_tot_other":"0","traders_noncomm_long_other":"0","traders_noncomm_short_other":"0","traders_noncomm_spread_other":"0","traders_comm_long_other":"0","traders_comm_short_other":"0","traders_tot_rept_long_other":"0","traders_tot_rept_short_other":"0","conc_gross_le_4_tdr_long":"45.5","conc_gross_le_4_tdr_short":"43.1","conc_gross_le_8_tdr_long":"58.7","conc_gross_le_8_tdr_short":"59.9","conc_net_le_4_tdr_long_all":"45.3","conc_net_le_4_tdr_short_all":"43.1","conc_net_le_8_tdr_long_all":"58.1","conc_net_le_8_tdr_short_all":"59.9","conc_gross_le_4_tdr_long_1":"45.5","conc_gross_le_4_tdr_short_1":"43.1","conc_gross_le_8_tdr_long_1":"58.7","conc_gross_le_8_tdr_short_1":"59.9","conc_net_le_4_tdr_long_old":"45.3","conc_net_le_4_tdr_short_old":"43.1","conc_net_le_8_tdr_long_old":"58.1","conc_net_le_8_tdr_short_old":"59.9","conc_gross_le_4_tdr_long_2":"0.0","conc_gross_le_4_tdr_short_2":"0.0","conc_gross_le_8_tdr_long_2":"0.0","conc_gross_le_8_tdr_short_2":"0.0","conc_net_le_4_tdr_long_other":"0.0","conc_net_le_4_tdr_short_other":"0.0","conc_net_le_8_tdr_long_other":"0.0","conc_net_le_8_tdr_short_other":"0.0","contract_units":"($5 X DJIA INDEX)","commodity":"DOW JONES BROAD BASED INDICES","commodity_subgroup_name":"STOCK INDICES","commodity_group_name":"FINANCIAL INSTRUMENTS","futonly_or_combined":"FutOnly"}
,{"id":"26032412460+F","market_and_exchange_names":"DJIA Consolidated - CHICAGO BOARD OF TRADE","report_date_as_yyyy_mm_dd":"2026-03-24T00:00:00.000","yyyy_report_week_ww":"2026 Report Week 12","contract_market_name":"DJIA Consolidated","cftc_contract_market_code":"12460+","cftc_market_code":"CBT ","cftc_region_code":"CHI","cftc_commodity_code":"124 ","commodity_name":"DOW JONES BROAD BASED INDICES","open_interest_all":"67922","noncomm_positions_long_all":"5330","noncomm_positions_short_all":"11893","noncomm_postions_spread_all":"1277","comm_positions_long_all":"48360","comm_positions_short_all":"45405","tot_rept_positions_long_all":"54967","tot_rept_positions_short":"58575","nonrept_positions_long_all":"12955","nonrept_positions_short_all":"9347","open_interest_old":"67922","noncomm_positions_long_old":"5330","noncomm_positions_short_old":"11893","noncomm_positions_spread":"1277","comm_positions_long_old":"48360","comm_positions_short_old":"45405","tot_rept_positions_long_old":"54967","tot_rept_positions_short_1":"58575","nonrept_positions_long_old":"12955","nonrept_positions_short_old":"9347","open_interest_other":"0","noncomm_positions_long_other":"0","noncomm_positions_short_other":"0","noncomm_positions_spread_1":"0","comm_positions_long_other":"0","comm_positions_short_other":"0","tot_rept_positions_long_other":"0","tot_rept_positions_short_2":"0","nonrept_positions_long_other":"0","nonrept_positions_short_other":"0","change_in_open_interest_all":"-28650","change_in_noncomm_long_all":"-7661","change_in_noncomm_short_all":"-2052","change_in_noncomm_spead_all":"-5893","change_in_comm_long_all":"-12032","change_in_comm_short_all":"-18200","change_in_tot_rept_long_all":"-25586","change_in_tot_rept_short":"-26144","change_in_nonrept_long_all":"-3064","change_in_nonrept_short_all":"-2505","pct_of_open_interest_all":"100.0","pct_of_oi_noncomm_long_all":"7.8","pct_of_oi_noncomm_short_all":"17.5","pct_of_oi_noncomm_spread":"1.9","pct_of_oi_comm_long_all":"71.2","pct_of_oi_comm_short_all":"66.8","pct_of_oi_tot_rept_long_all":"80.9","pct_of_oi_tot_rept_short":"86.2","pct_of_oi_nonrept_long_all":"19.1","pct_of_oi_nonrept_short_all":"13.8","pct_of_open_interest_old":"100.0","pct_of_oi_noncomm_long_old":"7.8","pct_of_oi_noncomm_short_old":"17.5","pct_of_oi_noncomm_spread_1":"1.9","pct_of_oi_comm_long_old":"71.2","pct_of_oi_comm_short_old":"66.8","pct_of_oi_tot_rept_long_old":"80.9","pct_of_oi_tot_rept_short_1":"86.2","pct_of_oi_nonrept_long_old":"19.1","pct_of_oi_nonrept_short_old":"13.8","pct_of_open_interest_other":"0.0","pct_of_oi_noncomm_long_other":"0.0","pct_of_oi_noncomm_short_other":"0.0","pct_of_oi_noncomm_spread_2":"0.0","pct_of_oi_comm_long_other":"0.0","pct_of_oi_comm_short_other":"0.0","pct_of_oi_tot_rept_long_other":"0.0","pct_of_oi_tot_rept_short_2":"0.0","pct_of_oi_nonrept_long_other":"0.0","pct_of_oi_nonrept_short_other":"0.0","traders_tot_all":"67","traders_noncomm_long_all":"11","traders_noncomm_short_all":"15","traders_noncomm_spread_all":"8","traders_comm_long_all":"27","traders_comm_short_all":"20","traders_tot_rept_long_all":"43","traders_tot_rept_short_all":"38","traders_tot_old":"67","traders_noncomm_long_old":"11","traders_noncomm_short_old":"15","traders_noncomm_spead_old":"8","traders_comm_long_old":"27","traders_comm_short_old":"20","traders_tot_rept_long_old":"43","traders_tot_rept_short_old":"38","traders_tot_other":"0","traders_noncomm_long_other":"0","traders_noncomm_short_other":"0","traders_noncomm_spread_other":"0","traders_comm_long_other":"0","traders_comm_short_other":"0","traders_tot_rept_long_other":"0","traders_tot_rept_short_other":"0","conc_gross_le_4_tdr_long":"46.2","conc_gross_le_4_tdr_short":"42.6","conc_gross_le_8_tdr_long":"59.7","conc_gross_le_8_tdr_short":"59.5","conc_net_le_4_tdr_long_all":"45.9","conc_net_le_4_tdr_short_all":"42.6","conc_net_le_8_tdr_long_all":"59.5","conc_net_le_8_tdr_short_all":"59.5","conc_gross_le_4_tdr_long_1":"46.2","conc_gross_le_4_tdr_short_1":"42.6","conc_gross_le_8_tdr_long_1":"59.7","conc_gross_le_8_tdr_short_1":"59.5","conc_net_le_4_tdr_long_old":"45.9","conc_net_le_4_tdr_short_old":"42.6","conc_net_le_8_tdr_long_old":"59.5","conc_net_le_8_tdr_short_old":"59.5","conc_gross_le_4_tdr_long_2":"0.0","conc_gross_le_4_tdr_short_2":"0.0","conc_gross_le_8_tdr_long_2":"0.0","conc_gross_le_8_tdr_short_2":"0.0","conc_net_le_4_tdr_long_other":"0.0","conc_net_le_4_tdr_short_other":"0.0","conc_net_le_8_tdr_long_other":"0.0","conc_net_le_8_tdr_short_other":"0.0","contract_units":"($5 X DJIA INDEX)","commodity":"DOW JONES BROAD BASED INDICES","commodity_subgroup_name":"STOCK INDICES","commodity_group_name":"FINANCIAL INSTRUMENTS","futonly_or_combined":"FutOnly"}
,{"id":"26031712460+F","market_and_exchange_names":"DJIA Consolidated - CHICAGO BOARD OF TRADE","report_date_as_yyyy_mm_dd":"2026-03-17T00:00:00.000","yyyy_report_week_ww":"2026 Report Week 11","contract_market_name":"DJIA Consolidated","cftc_contract_market_code":"12460+","cftc_market_code":"CBT ","cftc_region_code":"CHI","cftc_commodity_code":"124 ","commodity_name":"DOW JONES BROAD BASED INDICES","open_interest_all":"96572","noncomm_positions_long_all":"12991","noncomm_positions_short_all":"13945","noncomm_postions_spread_all":"7170","comm_positions_long_all":"60392","comm_positions_short_all":"63605","tot_rept_positions_long_all":"80553","tot_rept_positions_short":"84719","nonrept_positions_long_all":"16019","nonrept_positions_short_all":"11852","open_interest_old":"96572","noncomm_positions_long_old":"12991","noncomm_positions_short_old":"13945","noncomm_positions_spread":"7170","comm_positions_long_old":"60392","comm_positions_short_old":"63605","tot_rept_positions_long_old":"80553","tot_rept_positions_short_1":"84719","nonrept_positions_long_old":"16019","nonrept_positions_short_old":"11852","open_interest_other":"0","noncomm_positions_long_other":"0","noncomm_positions_short_other":"0","noncomm_positions_spread_1":"0","comm_positions_long_other":"0","comm_positions_short_other":"0","tot_rept_positions_long_other":"0","tot_rept_positions_short_2":"0","nonrept_positions_long_other":"0","nonrept_positions_short_other":"0","change_in_open_interest_all":"21588","change_in_noncomm_long_all":"-63","change_in_noncomm_short_all":"-2026","change_in_noncomm_spead_all":"1112","change_in_comm_long_all":"18460","change_in_comm_short_all":"21895","change_in_tot_rept_long_all":"19509","change_in_tot_rept_short":"20980","change_in_nonrept_long_all":"2079","change_in_nonrept_short_all":"608","pct_of_open_interest_all":"100.0","pct_of_oi_noncomm_long_all":"13.5","pct_of_oi_noncomm_short_all":"14.4","pct_of_oi_noncomm_spread":"7.4","pct_of_oi_comm_long_all":"62.5","pct_of_oi_comm_short_all":"65.9","pct_of_oi_tot_rept_long_all":"83.4","pct_of_oi_tot_rept_short":"87.7","pct_of_oi_nonrept_long_all":"16.6","pct_of_oi_nonrept_short_all":"12.3","pct_of_open_interest_old":"100.0","pct_of_oi_noncomm_long_old":"13.5","pct_of_oi_noncomm_short_old":"14.4","pct_of_oi_noncomm_spread_1":"7.4","pct_of_oi_comm_long_old":"62.5","pct_of_oi_comm_short_old":"65.9","pct_of_oi_tot_rept_long_old":"83.4","pct_of_oi_tot_rept_short_1":"87.7","pct_of_oi_nonrept_long_old":"16.6","pct_of_oi_nonrept_short_old":"12.3","pct_of_open_interest_other":"0.0","pct_of_oi_noncomm_long_other":"0.0","pct_of_oi_noncomm_short_other":"0.0","pct_of_oi_noncomm_spread_2":"0.0","pct_of_oi_comm_long_other":"0.0","pct_of_oi_comm_short_other":"0.0","pct_of_oi_tot_rept_long_other":"0.0","pct_of_oi_tot_rept_short_2":"0.0","pct_of_oi_nonrept_long_other":"0.0","pct_of_oi_nonrept_short_other":"0.0","traders_tot_all":"90","traders_noncomm_long_all":"19","traders_noncomm_short_all":"21","traders_noncomm_spread_all":"15","traders_comm_long_all":"37","traders_comm_short_all":"25","traders_tot_rept_long_all":"65","traders_tot_rept_short_all":"55","traders_tot_old":"90","traders_noncomm_long_old":"19","traders_noncomm_short_old":"21","traders_noncomm_spead_old":"15","traders_comm_long_old":"37","traders_comm_short_old":"25","traders_tot_rept_long_old":"65","traders_tot_rept_short_old":"55","traders_tot_other":"0","traders_noncomm_long_other":"0","traders_noncomm_short_other":"0","traders_noncomm_spread_other":"0","traders_comm_long_other":"0","traders_comm_short_other":"0","traders_tot_rept_long_other":"0","traders_tot_rept_short_other":"0","conc_gross_le_4_tdr_long":"36.5","conc_gross_le_4_tdr_short":"32.7","conc_gross_le_8_tdr_long":"50.8","conc_gross_le_8_tdr_short":"49.5","conc_net_le_4_tdr_long_all":"36.3","conc_net_le_4_tdr_short_all":"28.9","conc_net_le_8_tdr_long_all":"43.3","conc_net_le_8_tdr_short_all":"41.0","conc_gross_le_4_tdr_long_1":"36.5","conc_gross_le_4_tdr_short_1":"32.7","conc_gross_le_8_tdr_long_1":"50.8","conc_gross_le_8_tdr_short_1":"49.5","conc_net_le_4_tdr_long_old":"36.3","conc_net_le_4_tdr_short_old":"28.9","conc_net_le_8_tdr_long_old":"43.3","conc_net_le_8_tdr_short_old":"41.0","conc_gross_le_4_tdr_long_2":"0.0","conc_gross_le_4_tdr_short_2":"0.0","conc_gross_le_8_tdr_long_2":"0.0","conc_gross_le_8_tdr_short_2":"0.0","conc_net_le_4_tdr_long_other":"0.0","conc_net_le_4_tdr_short_other":"0.0","conc_net_le_8_tdr_long_other":"0.0","conc_net_le_8_tdr_short_other":"0.0","contract_units":"($5 X DJIA INDEX)","commodity":"DOW JONES BROAD BASED INDICES","commodity_subgroup_name":"STOCK INDICES","commodity_group_name":"FINANCIAL INSTRUMENTS","futonly_or_combined":"FutOnly"}]
